LICENSE
MANIFEST.in
README.md
requirements.txt
setup.py
hornbill4p/__init__.py
hornbill4p/__version__.py
hornbill4p/client.py
hornbill4p/hornbill_pb2.py
hornbill4p/hornbill_pb2_grpc.py
hornbill4p.egg-info/PKG-INFO
hornbill4p.egg-info/SOURCES.txt
hornbill4p.egg-info/dependency_links.txt
hornbill4p.egg-info/top_level.txt