Metadata-Version: 1.0
Name: hornbill4p
Version: 0.1.1
Summary: hornbill python client and util
Home-page: http://www.datastory.com.cn
Author: mouhao
Author-email: mouhao@hudongpai.com
License:                   DATASTORY Co. Ltd. LICENSE
